onebatterytest/__init__.py
onebatterytest/foo.py
onebatterytest-0.0.0.dist-info/METADATA
onebatterytest-0.0.0.dist-info/WHEEL
onebatterytest-0.0.0.dist-info/licenses/LICENSE
onebatterytest-0.0.0.dist-info/RECORD
