Metadata-Version: 2.4
Name: OneBatteryTest
Version: 0.0.0
Summary: For now, this is a placeholder and will be filled with code at a later development stage.
Project-URL: Homepage, https://LukasGold.github.io/OneBatteryTest/
Project-URL: Repository, https://github.com/LukasGold/OneBatteryTest
Project-URL: Documentation, https://LukasGold.github.io/OneBatteryTest/
Author-email: Lukas Gold <lukas.gold@isc.fraunhofer.de>
License-File: LICENSE
Keywords: python
Classifier: Intended Audience :: Developers
Classifier: Programming Language :: Python
Classifier: Programming Language :: Python :: 3
Classifier: Programming Language :: Python :: 3.9
Classifier: Programming Language :: Python :: 3.10
Classifier: Programming Language :: Python :: 3.11
Classifier: Programming Language :: Python :: 3.12
Classifier: Programming Language :: Python :: 3.13
Classifier: Topic :: Software Development :: Libraries :: Python Modules
Requires-Python: <4.0,>=3.9
